Duitku/__init__.py
Duitku/client.py
Duitku/invoice/__init__.py
Duitku/invoice/invoice.py
Duitku/invoice/models.py
Duitku/payment/__init__.py
Duitku/payment/models.py
Duitku/payment/payment.py
Duitku/transaction/__init__.py
Duitku/transaction/models.py
Duitku/transaction/transaction.py
duitku-0.2.10.dist-info/licenses/LICENSE
duitku-0.2.10.dist-info/METADATA
duitku-0.2.10.dist-info/WHEEL
duitku-0.2.10.dist-info/top_level.txt
duitku-0.2.10.dist-info/RECORD
