Metadata-Version: 2.4
Name: Duitku
Version: 0.2.10
Summary: Duitku Python SDK
Home-page: https://github.com/idoyudha/duitku-python
Author: Ido Yudhatama
Author-email: Ido Yudhatama <idowidya.yudhatama@gmail.com>
License-Expression: MIT
Project-URL: Homepage, https://github.com/idoyudha/duitku-python
Project-URL: Issues, https://github.com/idoyudha/duitku-python/issues
Classifier: Programming Language :: Python :: 3
Classifier: Operating System :: OS Independent
Requires-Python: >=3.5
License-File: LICENSE
Dynamic: author
Dynamic: home-page
Dynamic: license-file
Dynamic: requires-python
